graphics/__init__.py
graphics/common/__init__.py
graphics/common/logs.py
graphics/common/oss.py
graphics/common/utils.py
graphics/function/Analysis.py
graphics/function/Calculate.py
graphics/function/Classifier.py
graphics/function/Color.py
graphics/function/Detection.py
graphics/function/Evaluate.py
graphics/function/FaceDetector.py
graphics/function/FontWriter.py
graphics/function/Format.py
graphics/function/Graphics.py
graphics/function/ImageCrop.py
graphics/function/MachineLearning.py
graphics/function/MtcnnDetector.py
graphics/function/MultiLabelClassify.py
graphics/function/OcrDetector.py
graphics/function/Recognizer.py
graphics/function/SceneDetector.py
graphics/function/Segmentation.py
graphics/function/VideoCodec.py
graphics/function/VideoProcess.py
graphics/function/__init__.py
graphics/libs/__init__.py
graphics/libs/f3net.py
graphics/libs/craft/__init__.py
graphics/libs/craft/craft.py
graphics/libs/craft/vgg16_bn.py
graphics/libs/dbface/DBFace.py
graphics/libs/dbface/__init__.py
graphics/libs/mtcnn/__init__.py
graphics/libs/mtcnn/box_utils.py
graphics/libs/mtcnn/first_stage.py
graphics/libs/mtcnn/get_nets.py
graphics/libs/place365/__init__.py
graphics/libs/place365/wideresnet.py
graphics/libs/resnet/__init__.py
graphics/libs/resnet/cbam_resnet.py
graphics/libs/resnet/dataset.py
graphics/libs/resnet/logger.py
graphics/libs/resnet/network.py
graphics/libs/resnet/resnet_crnn.py
graphics/libs/resnet/se_resnet.py
graphics/libs/resnet/se_resnext.py
graphics/libs/resnet/snapshot.py
graphics/libs/yolact/__init__.py
graphics/libs/yolact/backbone.py
graphics/libs/yolact/box_utils.py
graphics/libs/yolact/config.py
graphics/libs/yolact/detection.py
graphics/libs/yolact/functions.py
graphics/libs/yolact/interpolate.py
graphics/libs/yolact/output_utils.py
graphics/libs/yolact/timer.py
graphics/libs/yolact/yolact.py
open_graphics-0.1.37.dist-info/METADATA
open_graphics-0.1.37.dist-info/WHEEL
open_graphics-0.1.37.dist-info/top_level.txt
open_graphics-0.1.37.dist-info/zip-safe
open_graphics-0.1.37.dist-info/RECORD
