Metadata-Version: 2.1
Name: open-graphics
Version: 0.1.37
Summary: Open Graphics Toolkit
Home-page: https://github.com/CachCheng/OpenGraphics
Author: CachCheng
Author-email: tkggpdc2007@163.com
License: Apache-2.0
Platform: UNKNOWN
Requires-Dist: oss2
Requires-Dist: requests
Requires-Dist: numpy
Requires-Dist: pandas
Requires-Dist: matplotlib
Requires-Dist: opencv-python
Requires-Dist: flask
Requires-Dist: colour-science
Requires-Dist: scikit-learn
Requires-Dist: scenedetect
Requires-Dist: moviepy
Requires-Dist: Pillow
Requires-Dist: torch
Requires-Dist: torchvision
Requires-Dist: joblib
Requires-Dist: tensorflow
Requires-Dist: tensorflow-hub
